OtlmowModel/BaseClasses/BooleanField.py
OtlmowModel/BaseClasses/CachedProperty.py
OtlmowModel/BaseClasses/ComplexField.py
OtlmowModel/BaseClasses/DateField.py
OtlmowModel/BaseClasses/DateTimeField.py
OtlmowModel/BaseClasses/DavieRelatieAttributes.py
OtlmowModel/BaseClasses/DteAssetType.py
OtlmowModel/BaseClasses/FloatOrDecimalField.py
OtlmowModel/BaseClasses/IntegerField.py
OtlmowModel/BaseClasses/KeuzelijstField.py
OtlmowModel/BaseClasses/KeuzelijstWaarde.py
OtlmowModel/BaseClasses/LiteralField.py
OtlmowModel/BaseClasses/MetaInfo.py
OtlmowModel/BaseClasses/NonNegIntegerField.py
OtlmowModel/BaseClasses/OTLAsset.py
OtlmowModel/BaseClasses/OTLField.py
OtlmowModel/BaseClasses/OTLObject.py
OtlmowModel/BaseClasses/RelationInteractor.py
OtlmowModel/BaseClasses/StringField.py
OtlmowModel/BaseClasses/TimeField.py
OtlmowModel/BaseClasses/URIField.py
OtlmowModel/BaseClasses/UnionTypeField.py
OtlmowModel/BaseClasses/UnionWaarden.py
OtlmowModel/BaseClasses/WKTField.py
OtlmowModel/BaseClasses/WKTValidator.py
OtlmowModel/BaseClasses/WaardenObject.py
OtlmowModel/Classes/Agent.py
OtlmowModel/Classes/Abstracten/AOWSType.py
OtlmowModel/Classes/Abstracten/AanhorighedenBrug.py
OtlmowModel/Classes/Abstracten/AanhorigheidKoker.py
OtlmowModel/Classes/Abstracten/AansluitendeConstructie.py
OtlmowModel/Classes/Abstracten/AbstracteAanvullendeGeometrie.py
OtlmowModel/Classes/Abstracten/AfmetingenDiepCBWand.py
OtlmowModel/Classes/Abstracten/AfschermendeConstructie.py
OtlmowModel/Classes/Abstracten/AfwijkendeKantopsluiting.py
OtlmowModel/Classes/Abstracten/AndereLaag.py
OtlmowModel/Classes/Abstracten/AndereVerharding.py
OtlmowModel/Classes/Abstracten/ArtificieleLaag.py
OtlmowModel/Classes/Abstracten/AxiaalDraagvermogen.py
OtlmowModel/Classes/Abstracten/AxiaalDraagvermogenWand.py
OtlmowModel/Classes/Abstracten/Bebakening.py
OtlmowModel/Classes/Abstracten/Beginstuk.py
OtlmowModel/Classes/Abstracten/BegroeidVoorkomen.py
OtlmowModel/Classes/Abstracten/Behuizing.py
otlmow_model-2.10.2.0.dist-info/LICENSE
otlmow_model-2.10.2.0.dist-info/METADATA
otlmow_model-2.10.2.0.dist-info/WHEEL
otlmow_model-2.10.2.0.dist-info/top_level.txt
otlmow_model-2.10.2.0.dist-info/RECORD
