Metadata-Version: 2.1
Name: otlmow_model
Version: 2.10.2.0
Author-email: David Vlaminck <david.vlaminck@mow.vlaanderen.be>
License: GNU GENERAL PUBLIC LICENSE
Project-URL: Homepage, https://github.com/davidvlaminck/OTLMOW-Model
Project-URL: Bug Tracker, https://github.com/davidvlaminck/OTLMOW-Model/issues
Classifier: Programming Language :: Python :: 3
Classifier: Programming Language :: Python :: 3.6
Classifier: Programming Language :: Python :: 3.7
Classifier: Programming Language :: Python :: 3.8
Classifier: Programming Language :: Python :: 3.9
Classifier: Programming Language :: Python :: 3.10
Classifier: Programming Language :: Python :: 3.11
Classifier: Operating System :: OS Independent
Classifier: Development Status :: 5 - Production/Stable
Classifier: Environment :: Console
Classifier: Intended Audience :: Developers
Classifier: Intended Audience :: Information Technology
Classifier: License :: OSI Approved :: GNU General Public License v3 (GPLv3)
Classifier: Natural Language :: Dutch
Classifier: Topic :: Software Development
Classifier: Topic :: Software Development :: Libraries :: Python Modules
Classifier: Topic :: Software Development :: Quality Assurance
Requires-Python: >=3.6
License-File: LICENSE
